{
  "openapi": "3.0.0",
  "info": {
    "title": "A10 aXAPI v3 Documentation - SET-PRODUCT-ID",
    "version": "3.0.0",
    "description": "Auto-generated documentation for the set-product-id category."
  },
  "servers": [
    {
      "url": "https://{thunder_ip}/axapi/v3",
      "variables": {
        "thunder_ip": {
          "default": "thunder.example.com",
          "description": "IP address or hostname of the Thunder device"
        }
      }
    }
  ],
  "paths": {
    "/axapi/v3/set-product-id": {
      "parameters": [],
      "get": {
        "tags": [
          "SET-PRODUCT-ID"
        ],
        "description": "Set product ID",
        "responses": {
          "200": {
            "description": "Successful response",
            "content": {
              "application/json": {
                "schema": {
                  "$ref": "#/components/schemas/set-product-id"
                }
              }
            }
          }
        }
      },
      "post": {
        "tags": [
          "SET-PRODUCT-ID"
        ],
        "description": "Set product ID",
        "responses": {
          "200": {
            "description": "Successful response",
            "content": {
              "application/json": {
                "schema": {
                  "$ref": "#/components/schemas/set-product-id"
                }
              }
            }
          }
        },
        "requestBody": {
          "content": {
            "application/json": {
              "schema": {
                "$ref": "#/components/schemas/set-product-id"
              }
            }
          }
        }
      }
    }
  },
  "components": {
    "schemas": {
      "set-product-id": {
        "type": "object",
        "properties": {
          "id": {
            "type": "number",
            "description": "Enter the desired product ID, default is 2",
            "minimum": 0,
            "maximum": 9
          }
        }
      }
    },
    "securitySchemes": {
      "SessionToken": {
        "type": "apiKey",
        "in": "header",
        "name": "Authorization",
        "description": "ACOS Session Token (e.g., A10 {token})"
      }
    }
  },
  "security": [
    {
      "SessionToken": []
    }
  ]
}